random_object_id.py
random_object_id-2.0.0.dist-info/LICENSE
random_object_id-2.0.0.dist-info/METADATA
random_object_id-2.0.0.dist-info/WHEEL
random_object_id-2.0.0.dist-info/entry_points.txt
random_object_id-2.0.0.dist-info/top_level.txt
random_object_id-2.0.0.dist-info/RECORD
