Metadata-Version: 2.1
Name: random-object-id
Version: 2.0.0
Summary: Generate a random MongoDB ObjectId.
Home-page: https://github.com/mxr/random-object-id
Author: Max R
Author-email: maxr@outlook.com
License: MIT
Keywords: random test MongoDB mongo ObjectId
Platform: UNKNOWN
Classifier: License :: OSI Approved :: MIT License
Classifier: Programming Language :: Python :: 3
Classifier: Programming Language :: Python :: 3 :: Only
Classifier: Programming Language :: Python :: 3.6
Classifier: Programming Language :: Python :: 3.7
Classifier: Programming Language :: Python :: 3.8
Classifier: Programming Language :: Python :: Implementation :: CPython
Classifier: Programming Language :: Python :: Implementation :: PyPy
Requires-Python: >=3.6.1
